PythonChessLibrary/__init__.py
PythonChessLibrary/game.py
PythonChessLibrary/player.py
PythonChessLibrary/tools.py
PythonChessLibrary-0.0.3.dist-info/LICENSE
PythonChessLibrary-0.0.3.dist-info/METADATA
PythonChessLibrary-0.0.3.dist-info/WHEEL
PythonChessLibrary-0.0.3.dist-info/top_level.txt
PythonChessLibrary-0.0.3.dist-info/RECORD
