Metadata-Version: 2.1
Name: PythonChessLibrary
Version: 0.0.3
Summary: Simple library to add relevant classes for a chess game.
Home-page: https://github.com/jschultz38/PythonChessLibrary
Author: Jarrett S
Author-email: jschultz38@gatech.edu
License: LICENSE
Keywords: chess
Platform: UNKNOWN
License-File: LICENSE
